EXP 4/priority_encoder_4to2/priority_encoder_4to2.v
`timescale 1ns/1ps

module priority_encoder_4to2 (
    input  wire I3,
    input  wire I2,
    input  wire I1,
    input  wire I0,
    output wire Y1,
    output wire Y0,
    output wire valid
);

assign Y1    = I3 | ((~I3) & I2);
assign Y0    = I3 | ((~I3) & (~I2) & I1);
assign valid = I3 | I2 | I1 | I0;

endmodule

EXP 1/priority_encoder_4to2/priority_encoder_4to2_tb.v
`timescale 1ns/1ps

module priority_encoder_4to2_tb;

reg I3;
reg I2;
reg I1;
reg I0;

wire Y1;
wire Y0;
wire valid;

reg expected_Y1;
reg expected_Y0;
reg expected_valid;
integer input_value;
integer pass_count;

priority_encoder_4to2 uut (
    .I3(I3),
    .I2(I2),
    .I1(I1),
    .I0(I0),
    .Y1(Y1),
    .Y0(Y0),
    .valid(valid)
);

initial begin
    $dumpfile("EXP 1/priority_encoder_4to2/priority_encoder_4to2.vcd");
    $dumpvars(0, priority_encoder_4to2_tb);

    pass_count = 0;
    $display("---------------------------------------------------------------");
    $display(" I3 I2 I1 I0 | Y1 Y0 valid | E_Y1 E_Y0 E_valid | Status");
    $display("---------------------------------------------------------------");

    for (input_value = 0; input_value < 16; input_value = input_value + 1) begin
        {I3, I2, I1, I0} = input_value[3:0];

        if (I3) begin
            expected_Y1 = 1'b1;
            expected_Y0 = 1'b1;
            expected_valid = 1'b1;
        end else if (I2) begin
            expected_Y1 = 1'b1;
            expected_Y0 = 1'b0;
            expected_valid = 1'b1;
        end else if (I1) begin
            expected_Y1 = 1'b0;
            expected_Y0 = 1'b1;
            expected_valid = 1'b1;
        end else if (I0) begin
            expected_Y1 = 1'b0;
            expected_Y0 = 1'b0;
            expected_valid = 1'b1;
        end else begin
            expected_Y1 = 1'b0;
            expected_Y0 = 1'b0;
            expected_valid = 1'b0;
        end

        #1;
        if ({Y1, Y0, valid} !== {expected_Y1, expected_Y0, expected_valid}) begin
            $display(" %b  %b  %b  %b |  %b  %b    %b   |   %b     %b      %b   | FAIL",
                     I3, I2, I1, I0, Y1, Y0, valid,
                     expected_Y1, expected_Y0, expected_valid);
            $fatal(1, "Mismatch for input %b%b%b%b", I3, I2, I1, I0);
        end

        pass_count = pass_count + 1;
        $display(" %b  %b  %b  %b |  %b  %b    %b   |   %b     %b      %b   | PASS",
                 I3, I2, I1, I0, Y1, Y0, valid,
                 expected_Y1, expected_Y0, expected_valid);
    end

    $display("---------------------------------------------------------------");
    $display("All %0d priority encoder input combinations passed.", pass_count);
    $finish;
end

endmodule

EXP 1/priority_encoder_4to2/priority_encoder_4to2.vcd
$date
	Fri Aug 21 13:26:57 2026
$end
$version
	Icarus Verilog
$end
$timescale
	1ps
$end
$scope module priority_encoder_4to2_tb $end
$var wire 1 ! valid $end
$var wire 1 " Y1 $end
$var wire 1 # Y0 $end
$var reg 1 $ I0 $end
$var reg 1 % I1 $end
$var reg 1 & I2 $end
$var reg 1 ' I3 $end
$var reg 1 ( expected_Y0 $end
$var reg 1 ) expected_Y1 $end
$var reg 1 * expected_valid $end
$var integer 32 + input_value [31:0] $end
$var integer 32 , pass_count [31:0] $end
$scope module uut $end
$var wire 1 $ I0 $end
$var wire 1 % I1 $end
$var wire 1 & I2 $end
$var wire 1 ' I3 $end
$var wire 1 # Y0 $end
$var wire 1 " Y1 $end
$var wire 1 ! valid $end
$upscope $end
$upscope $end
$enddefinitions $end
#0
$dumpvars
b0 ,
b0 +
0*
0)
0(
0'
0&
0%
0$
0#
0"
0!
$end
#1000
1!
1*
1$
b1 +
b1 ,
#2000
1#
1!
1(
1%
0$
b10 +
b10 ,
#3000
1$
b11 +
b11 ,
#4000
1"
0#
1!
0(
1)
1&
0%
0$
b100 +
b100 ,
#5000
1$
b101 +
b101 ,
#6000
1%
0$
b110 +
b110 ,
#7000
1$
b111 +
b111 ,
#8000
1#
1(
1'
0&
0%
0$
b1000 +
b1000 ,
#9000
1$
b1001 +
b1001 ,
#10000
1%
0$
b1010 +
b1010 ,
#11000
1$
b1011 +
b1011 ,
#12000
1&
0%
0$
b1100 +
b1100 ,
#13000
1$
b1101 +
b1101 ,
#14000
1%
0$
b1110 +
b1110 ,
#15000
1$
b1111 +
b1111 ,
#16000
b10000 +
b10000 ,
