EXP 2/mux2_behavioral.v
module mux2_behavioral (
    input  wire d0,
    input  wire d1,
    input  wire sel,
    output reg  y
);
    always @(*) begin
        if (sel == 1'b0)
            y = d0;
        else
            y = d1;
    end
endmodule

EXP 2/mux2_behavioral_tb.v
`timescale 1ns/1ps

module mux2_behavioral_tb;
    reg  d0, d1, sel;
    wire y;
    integer i;

    mux2_behavioral dut (.d0(d0), .d1(d1), .sel(sel), .y(y));

    initial begin
        $dumpfile("mux2_behavioral.vcd");
        $dumpvars(0, mux2_behavioral_tb);

        for (i = 0; i < 8; i = i + 1) begin
            {d1, d0, sel} = i;
            #10;
        end

        $finish;
    end
endmodule

EXP 2/mux2_behavioral.vcd
$date
	Thu Aug 20 11:20:24 2026
$end
$version
	Icarus Verilog
$end
$timescale
	1ps
$end
$scope module mux2_behavioral_tb $end
$var wire 1 ! y $end
$var reg 1 " d0 $end
$var reg 1 # d1 $end
$var reg 1 $ sel $end
$var integer 32 % i [31:0] $end
$scope module dut $end
$var wire 1 " d0 $end
$var wire 1 # d1 $end
$var wire 1 $ sel $end
$var reg 1 ! y $end
$upscope $end
$upscope $end
$enddefinitions $end
#0
$dumpvars
b0 %
0$
0#
0"
0!
$end
#10000
1$
b1 %
#20000
1!
1"
0$
b10 %
#30000
0!
1$
b11 %
#40000
1#
0"
0$
b100 %
#50000
1!
1$
b101 %
#60000
1"
0$
b110 %
#70000
1$
b111 %
#80000
b1000 %
