EXP 2/mux4_dataflow.v
module mux4_dataflow (
    input  wire [3:0] d,
    input  wire [1:0] sel,
    output wire        y
);
    assign y = (sel == 2'b00) ? d[0] :
               (sel == 2'b01) ? d[1] :
               (sel == 2'b10) ? d[2] : d[3];
endmodule

EXP 2/mux4_dataflow_tb.v
`timescale 1ns/1ps

module mux4_dataflow_tb;
    reg  [3:0] d;
    reg  [1:0] sel;
    wire       y;
    integer    i;

    mux4_dataflow dut (.d(d), .sel(sel), .y(y));

    initial begin
        $dumpfile("mux4_dataflow.vcd");
        $dumpvars(0, mux4_dataflow_tb);

        for (i = 0; i < 16; i = i + 1) begin
            d = i;
            sel = 2'b00;
            #10;
            sel = 2'b01;
            #10;
            sel = 2'b10;
            #10;
            sel = 2'b11;
            #10;
        end

        $finish;
    end
endmodule

EXP 2/mux4_dataflow.vcd
$date
	Thu Aug 20 11:20:24 2026
$end
$version
	Icarus Verilog
$end
$timescale
	1ps
$end
$scope module mux4_dataflow_tb $end
$var wire 1 ! y $end
$var reg 4 " d [3:0] $end
$var reg 2 # sel [1:0] $end
$var integer 32 $ i [31:0] $end
$scope module dut $end
$var wire 4 % d [3:0] $end
$var wire 2 & sel [1:0] $end
$var wire 1 ! y $end
$upscope $end
$upscope $end
$enddefinitions $end
#0
$dumpvars
b0 &
b0 %
b0 $
b0 #
b0 "
0!
$end
#10000
b1 #
b1 &
#20000
b10 #
b10 &
#30000
b11 #
b11 &
#40000
1!
b0 #
b0 &
b1 "
b1 %
b1 $
#50000
0!
b1 #
b1 &
#60000
b10 #
b10 &
#70000
b11 #
b11 &
#80000
b0 #
b0 &
b10 "
b10 %
b10 $
#90000
1!
b1 #
b1 &
#100000
0!
b10 #
b10 &
#110000
b11 #
b11 &
#120000
1!
b0 #
b0 &
b11 "
b11 %
b11 $
#130000
b1 #
b1 &
#140000
0!
b10 #
b10 &
#150000
b11 #
b11 &
#160000
b0 #
b0 &
b100 "
b100 %
b100 $
#170000
b1 #
b1 &
#180000
1!
b10 #
b10 &
#190000
0!
b11 #
b11 &
#200000
1!
b0 #
b0 &
b101 "
b101 %
b101 $
#210000
0!
b1 #
b1 &
#220000
1!
b10 #
b10 &
#230000
0!
b11 #
b11 &
#240000
b0 #
b0 &
b110 "
b110 %
b110 $
#250000
1!
b1 #
b1 &
#260000
b10 #
b10 &
#270000
0!
b11 #
b11 &
#280000
1!
b0 #
b0 &
b111 "
b111 %
b111 $
#290000
b1 #
b1 &
#300000
b10 #
b10 &
#310000
0!
b11 #
b11 &
#320000
b0 #
b0 &
b1000 "
b1000 %
b1000 $
#330000
b1 #
b1 &
#340000
b10 #
b10 &
#350000
1!
b11 #
b11 &
#360000
b0 #
b0 &
b1001 "
b1001 %
b1001 $
#370000
0!
b1 #
b1 &
#380000
b10 #
b10 &
#390000
1!
b11 #
b11 &
#400000
0!
b0 #
b0 &
b1010 "
b1010 %
b1010 $
#410000
1!
b1 #
b1 &
#420000
0!
b10 #
b10 &
#430000
1!
b11 #
b11 &
#440000
b0 #
b0 &
b1011 "
b1011 %
b1011 $
#450000
b1 #
b1 &
#460000
0!
b10 #
b10 &
#470000
1!
b11 #
b11 &
#480000
0!
b0 #
b0 &
b1100 "
b1100 %
b1100 $
#490000
b1 #
b1 &
#500000
1!
b10 #
b10 &
#510000
b11 #
b11 &
#520000
b0 #
b0 &
b1101 "
b1101 %
b1101 $
#530000
0!
b1 #
b1 &
#540000
1!
b10 #
b10 &
#550000
b11 #
b11 &
#560000
0!
b0 #
b0 &
b1110 "
b1110 %
b1110 $
#570000
1!
b1 #
b1 &
#580000
b10 #
b10 &
#590000
b11 #
b11 &
#600000
b0 #
b0 &
b1111 "
b1111 %
b1111 $
#610000
b1 #
b1 &
#620000
b10 #
b10 &
#630000
b11 #
b11 &
#640000
b10000 $
