EXP 3/FULL_ADDER/full_adder.v
module full_adder(
    input A,
    input B,
    input Cin,
    output Sum,
    output Carry
);

assign Sum = A ^ B ^ Cin;
assign Carry = (A & B) | (B & Cin) | (A & Cin);

endmodule

EXP 3/FULL_ADDER/full_adder_tb.v
`timescale 1ns/1ps

module full_adder_tb;

reg A;
reg B;
reg Cin;

wire Sum;
wire Carry;

full_adder uut (
    .A(A),
    .B(B),
    .Cin(Cin),
    .Sum(Sum),
    .Carry(Carry)
);

initial
begin
    $dumpfile("full_adder.vcd");
    $dumpvars(0, full_adder_tb);

    $display("A B Cin | Sum Carry");
    $monitor("%b %b  %b  |  %b    %b", A, B, Cin, Sum, Carry);

    A=0; B=0; Cin=0;
    #10;

    A=0; B=0; Cin=1;
    #10;

    A=0; B=1; Cin=0;
    #10;

    A=0; B=1; Cin=1;
    #10;

    A=1; B=0; Cin=0;
    #10;

    A=1; B=0; Cin=1;
    #10;

    A=1; B=1; Cin=0;
    #10;

    A=1; B=1; Cin=1;
    #10;

    $finish;
end

endmodule

EXP 3/FULL_ADDER/full_adder.vcd
$date
	Fri Aug 21 15:18:16 2026
$end
$version
	Icarus Verilog
$end
$timescale
	1ps
$end
$scope module full_adder_tb $end
$var wire 1 ! Sum $end
$var wire 1 " Carry $end
$var reg 1 # A $end
$var reg 1 $ B $end
$var reg 1 % Cin $end
$scope module uut $end
$var wire 1 # A $end
$var wire 1 $ B $end
$var wire 1 " Carry $end
$var wire 1 % Cin $end
$var wire 1 ! Sum $end
$upscope $end
$upscope $end
$enddefinitions $end
#0
$dumpvars
0%
0$
0#
0"
0!
$end
#10000
1!
1%
#20000
0%
1$
#30000
1"
0!
1%
#40000
0"
1!
0%
0$
1#
#50000
1"
0!
1%
#60000
0%
1$
#70000
1!
1%
